spacy2df/README.MD
spacy2df/__init__.py
spacy2df/requirements.txt
spacy2df/thirdparty.json
spacy2df-0.10.dist-info/LICENSE.rst
spacy2df-0.10.dist-info/METADATA
spacy2df-0.10.dist-info/WHEEL
spacy2df-0.10.dist-info/top_level.txt
spacy2df-0.10.dist-info/RECORD
