Metadata-Version: 2.1
Name: spacy2df
Version: 0.10
Summary: converts a spaCy object into a pandas DataFrame
Home-page: https://github.com/hansalemaos/spacy2df
Author: Johannes Fischer
Author-email: aulasparticularesdealemaosp@gmail.com
License: MIT
Keywords: spacy,nlp,pandas,DataFrame
Classifier: Development Status :: 4 - Beta
Classifier: Programming Language :: Python :: 3 :: Only
Classifier: Programming Language :: Python :: 3.10
Classifier: Topic :: Software Development :: Libraries :: Python Modules
Classifier: Topic :: Utilities
License-File: LICENSE.rst
Requires-Dist: a-pandas-ex-apply-ignore-exceptions
Requires-Dist: a-pandas-ex-less-memory-more-speed
Requires-Dist: dict-merger-keep-all
Requires-Dist: pandas
